sudoku/__init__.py
sudoku/sudoku.py
sudoku/test.py
sudoku_create-0.0.1.dist-info/LICENSE.txt
sudoku_create-0.0.1.dist-info/METADATA
sudoku_create-0.0.1.dist-info/WHEEL
sudoku_create-0.0.1.dist-info/top_level.txt
sudoku_create-0.0.1.dist-info/RECORD
