Metadata-Version: 2.1
Name: sudoku-create
Version: 0.0.1
Summary: A Python package to create a pair of solve and unsolve sudoku.
Home-page: https://github.com/kush-savani/Sudoku.git
Author: Kaushal Savani
Author-email: kaushalsavani@gmail.com
License: MIT
Platform: UNKNOWN
Classifier: Programming Language :: Python :: 3
Classifier: License :: OSI Approved :: MIT License
Classifier: Operating System :: OS Independent
Requires-Python: >=3
